etl_pipeline_ggn1_ase_g5/__init__.py
etl_pipeline_ggn1_ase_g5/__main__.py
etl_pipeline_ggn1_ase_g5/etl_db_manager.py
etl_pipeline_ggn1_ase_g5/etl_task.py
etl_pipeline_ggn1_ase_g5/utility.py
etl_pipeline_ggn1_ase_g5-4.1.dist-info/METADATA
etl_pipeline_ggn1_ase_g5-4.1.dist-info/WHEEL
etl_pipeline_ggn1_ase_g5-4.1.dist-info/entry_points.txt
etl_pipeline_ggn1_ase_g5-4.1.dist-info/top_level.txt
etl_pipeline_ggn1_ase_g5-4.1.dist-info/RECORD
