Metadata-Version: 2.1
Name: etl-pipeline-ggn1-ase-g5
Version: 4.1
Requires-Dist: dill
Requires-Dist: fastapi
Requires-Dist: schedule
Requires-Dist: uvicorn
Requires-Dist: pandas
